[
  {
    "student": "NAVEEN",
    "subject": "Math",
    "test_name": "Math Test 1",
    "score": 5,
    "total": 5,
    "percentage": 100.0,
    "duration_seconds": 12,
    "completed_before_timeout": true,
    "start_time": "2026-05-30T15:28:10.519091",
    "end_time": "2026-05-30T15:28:22.948742",
    "answers": [
      {
        "question": "5 + 3 = ?",
        "selected": "8",
        "correct": "8",
        "is_correct": true
      },
      {
        "question": "9 - 4 = ?",
        "selected": "5",
        "correct": "5",
        "is_correct": true
      },
      {
        "question": "7 + 2 = ?",
        "selected": "9",
        "correct": "9",
        "is_correct": true
      },
      {
        "question": "10 - 6 = ?",
        "selected": "4",
        "correct": "4",
        "is_correct": true
      },
      {
        "question": "4 + 5 = ?",
        "selected": "9",
        "correct": "9",
        "is_correct": true
      }
    ]
  },
  {
    "student": "NAVEEN",
    "subject": "Math",
    "test_name": "Math Test 1",
    "score": 1,
    "total": 5,
    "percentage": 20.0,
    "duration_seconds": 8,
    "completed_before_timeout": true,
    "start_time": "2026-05-30T15:31:56.847741",
    "end_time": "2026-05-30T15:32:04.811222",
    "answers": [
      {
        "question": "5 + 3 = ?",
        "selected": "6",
        "correct": "8",
        "is_correct": false
      },
      {
        "question": "9 - 4 = ?",
        "selected": "4",
        "correct": "5",
        "is_correct": false
      },
      {
        "question": "7 + 2 = ?",
        "selected": "8",
        "correct": "9",
        "is_correct": false
      },
      {
        "question": "10 - 6 = ?",
        "selected": "4",
        "correct": "4",
        "is_correct": true
      },
      {
        "question": "4 + 5 = ?",
        "selected": "8",
        "correct": "9",
        "is_correct": false
      }
    ]
  },
  {
    "student": "NAVEEN",
    "subject": "English",
    "test_name": "English Test 1",
    "score": 1,
    "total": 5,
    "percentage": 20.0,
    "duration_seconds": 9,
    "completed_before_timeout": true,
    "start_time": "2026-05-30T15:44:37.108334",
    "end_time": "2026-05-30T15:44:46.396171",
    "answers": [
      {
        "question": "What is the dog's name?",
        "selected": "Max",
        "correct": "Max",
        "is_correct": true
      },
      {
        "question": "Where do Tom and Max go?",
        "selected": "Mall",
        "correct": "Park",
        "is_correct": false
      },
      {
        "question": "What does Max like to do?",
        "selected": "Read",
        "correct": "Run and play",
        "is_correct": false
      },
      {
        "question": "Who owns Max?",
        "selected": "Ben",
        "correct": "Tom",
        "is_correct": false
      },
      {
        "question": "How often do they go to the park?",
        "selected": "Never",
        "correct": "Every day",
        "is_correct": false
      }
    ]
  },
  {
    "student": "NAHUSH",
    "subject": "Math",
    "test_name": "Math Test 1",
    "score": 5,
    "total": 5,
    "percentage": 100.0,
    "duration_seconds": 170,
    "completed_before_timeout": true,
    "start_time": "2026-05-30T16:39:43.232339",
    "end_time": "2026-05-30T16:42:33.227704",
    "answers": [
      {
        "question": "5 + 3 = ?",
        "selected": "8",
        "correct": "8",
        "is_correct": true
      },
      {
        "question": "9 - 4 = ?",
        "selected": "5",
        "correct": "5",
        "is_correct": true
      },
      {
        "question": "7 + 2 = ?",
        "selected": "9",
        "correct": "9",
        "is_correct": true
      },
      {
        "question": "10 - 6 = ?",
        "selected": "4",
        "correct": "4",
        "is_correct": true
      },
      {
        "question": "4 + 5 = ?",
        "selected": "9",
        "correct": "9",
        "is_correct": true
      }
    ]
  },
  {
    "student": "NAMMI",
    "subject": "Math",
    "test_name": "Math Test 1",
    "score": 3,
    "total": 5,
    "percentage": 60.0,
    "duration_seconds": 13,
    "completed_before_timeout": true,
    "start_time": "2026-05-30T17:54:23.551729",
    "end_time": "2026-05-30T17:54:36.285515",
    "answers": [
      {
        "question": "5 + 3 = ?",
        "selected": "8",
        "correct": "8",
        "is_correct": true
      },
      {
        "question": "9 - 4 = ?",
        "selected": "5",
        "correct": "5",
        "is_correct": true
      },
      {
        "question": "7 + 2 = ?",
        "selected": "8",
        "correct": "9",
        "is_correct": false
      },
      {
        "question": "10 - 6 = ?",
        "selected": "4",
        "correct": "4",
        "is_correct": true
      },
      {
        "question": "4 + 5 = ?",
        "selected": "10",
        "correct": "9",
        "is_correct": false
      }
    ]
  },
  {
    "student": "NAVEEN NAMMI",
    "subject": "Math",
    "test_name": "Math Test 3",
    "score": 0,
    "total": 6,
    "percentage": 0.0,
    "duration_seconds": 9,
    "completed_before_timeout": true,
    "start_time": "2026-05-30T18:08:18.228992",
    "end_time": "2026-05-30T18:08:27.437355",
    "answers": [
      {
        "question": "5 + 3 = ?",
        "selected": "Not Answered",
        "correct": "8",
        "is_correct": false,
        "type": "mcq"
      },
      {
        "question": "9 - 4 = ?",
        "selected": "Not Answered",
        "correct": "5",
        "is_correct": false,
        "type": "mcq"
      },
      {
        "question": "7 + 2 = ?",
        "selected": "Not Answered",
        "correct": "9",
        "is_correct": false,
        "type": "mcq"
      },
      {
        "question": "10 - 6 = ?",
        "selected": "Not Answered",
        "correct": "4",
        "is_correct": false,
        "type": "mcq"
      },
      {
        "question": "4 + 5 = ?",
        "selected": "Not Answered",
        "correct": "9",
        "is_correct": false,
        "type": "mcq"
      },
      {
        "question": "Julie counts 23 fish in one pond. She counts 13 more fish in another pond. How many fish does Julie count altogether?",
        "selected": "26",
        "correct": "36",
        "is_correct": false,
        "type": "fill"
      }
    ]
  },
  {
    "student": "NAMMI",
    "subject": "Math",
    "test_name": "Math Test 3",
    "score": 0,
    "total": 6,
    "percentage": 0.0,
    "duration_seconds": 7,
    "completed_before_timeout": true,
    "start_time": "2026-05-30T18:08:53.588478",
    "end_time": "2026-05-30T18:09:00.486038",
    "answers": [
      {
        "question": "5 + 3 = ?",
        "selected": "Not Answered",
        "correct": "8",
        "is_correct": false,
        "type": "mcq"
      },
      {
        "question": "9 - 4 = ?",
        "selected": "Not Answered",
        "correct": "5",
        "is_correct": false,
        "type": "mcq"
      },
      {
        "question": "7 + 2 = ?",
        "selected": "Not Answered",
        "correct": "9",
        "is_correct": false,
        "type": "mcq"
      },
      {
        "question": "10 - 6 = ?",
        "selected": "Not Answered",
        "correct": "4",
        "is_correct": false,
        "type": "mcq"
      },
      {
        "question": "4 + 5 = ?",
        "selected": "Not Answered",
        "correct": "9",
        "is_correct": false,
        "type": "mcq"
      },
      {
        "question": "Julie counts 23 fish in one pond. She counts 13 more fish in another pond. How many fish does Julie count altogether?",
        "selected": "26",
        "correct": "36",
        "is_correct": false,
        "type": "fill"
      }
    ]
  },
  {
    "student": "NAMMI",
    "subject": "Math",
    "test_name": "Math Test 3",
    "score": 1,
    "total": 6,
    "percentage": 16.7,
    "duration_seconds": 6,
    "completed_before_timeout": true,
    "start_time": "2026-05-30T18:09:19.758663",
    "end_time": "2026-05-30T18:09:25.812837",
    "answers": [
      {
        "question": "5 + 3 = ?",
        "selected": "Not Answered",
        "correct": "8",
        "is_correct": false,
        "type": "mcq"
      },
      {
        "question": "9 - 4 = ?",
        "selected": "Not Answered",
        "correct": "5",
        "is_correct": false,
        "type": "mcq"
      },
      {
        "question": "7 + 2 = ?",
        "selected": "Not Answered",
        "correct": "9",
        "is_correct": false,
        "type": "mcq"
      },
      {
        "question": "10 - 6 = ?",
        "selected": "Not Answered",
        "correct": "4",
        "is_correct": false,
        "type": "mcq"
      },
      {
        "question": "4 + 5 = ?",
        "selected": "Not Answered",
        "correct": "9",
        "is_correct": false,
        "type": "mcq"
      },
      {
        "question": "Julie counts 23 fish in one pond. She counts 13 more fish in another pond. How many fish does Julie count altogether?",
        "selected": "36",
        "correct": "36",
        "is_correct": true,
        "type": "fill"
      }
    ]
  },
  {
    "student": "NAMMI",
    "subject": "Math",
    "test_name": "Math Test 2",
    "score": 1,
    "total": 5,
    "percentage": 20.0,
    "duration_seconds": 4,
    "completed_before_timeout": true,
    "start_time": "2026-05-30T18:10:03.657670",
    "end_time": "2026-05-30T18:10:07.736122",
    "answers": [
      {
        "question": "Tom has 4 apples. He gets 3 more. How many apples does he have now?",
        "selected": "8",
        "correct": "7",
        "is_correct": false,
        "type": "mcq"
      },
      {
        "question": "Sara has 10 balloons. 2 fly away. How many are left?",
        "selected": "Not Answered",
        "correct": "8",
        "is_correct": false,
        "type": "mcq"
      },
      {
        "question": "There are 5 birds on a tree. 4 more join them. How many birds are there?",
        "selected": "9",
        "correct": "9",
        "is_correct": true,
        "type": "mcq"
      },
      {
        "question": "A box has 12 crayons. 3 are used. How many remain?",
        "selected": "Not Answered",
        "correct": "9",
        "is_correct": false,
        "type": "mcq"
      },
      {
        "question": "Ben has 6 toy cars and gets 2 more. How many cars does he have?",
        "selected": "Not Answered",
        "correct": "8",
        "is_correct": false,
        "type": "mcq"
      }
    ]
  },
  {
    "student": "NAHUSH",
    "subject": "Math",
    "test_name": "Math Test 3",
    "score": 5,
    "total": 6,
    "percentage": 83.3,
    "duration_seconds": 20,
    "completed_before_timeout": true,
    "start_time": "2026-05-30T18:19:57.919290",
    "end_time": "2026-05-30T18:20:17.937391",
    "answers": [
      {
        "question": "5 + 3 = ?",
        "selected": "8",
        "correct": "8",
        "is_correct": true
      },
      {
        "question": "9 - 4 = ?",
        "selected": "5",
        "correct": "5",
        "is_correct": true
      },
      {
        "question": "7 + 2 = ?",
        "selected": "9",
        "correct": "9",
        "is_correct": true
      },
      {
        "question": "10 - 6 = ?",
        "selected": "4",
        "correct": "4",
        "is_correct": true
      },
      {
        "question": "4 + 5 = ?",
        "selected": "9",
        "correct": "9",
        "is_correct": true
      },
      {
        "question": "Julie counts 23 fish in one pond. She counts 13 more fish in another pond. How many fish does Julie count altogether?",
        "selected": "26",
        "correct": "36",
        "is_correct": false
      }
    ]
  },
  {
    "student": "NAVEEN KUMAR",
    "subject": "Math",
    "test_name": "Math Test 1",
    "score": 2,
    "total": 5,
    "percentage": 40.0,
    "duration_seconds": 14,
    "completed_before_timeout": true,
    "start_time": "2026-05-30T18:27:22.116895",
    "end_time": "2026-05-30T18:27:36.514337",
    "answers": [
      {
        "question": "5 + 3 = ?",
        "selected": "6",
        "correct": "8",
        "is_correct": false
      },
      {
        "question": "9 - 4 = ?",
        "selected": "4",
        "correct": "5",
        "is_correct": false
      },
      {
        "question": "7 + 2 = ?",
        "selected": "9",
        "correct": "9",
        "is_correct": true
      },
      {
        "question": "10 - 6 = ?",
        "selected": "5",
        "correct": "4",
        "is_correct": false
      },
      {
        "question": "4 + 5 = ?",
        "selected": "9",
        "correct": "9",
        "is_correct": true
      }
    ]
  },
  {
    "student": "TEST",
    "subject": "Math",
    "test_name": "Math Assignment - 1",
    "score": 5,
    "total": 20,
    "percentage": 25.0,
    "duration_seconds": 43,
    "completed_before_timeout": true,
    "start_time": "2026-05-30T19:20:55.005074",
    "end_time": "2026-05-30T19:21:38.346561",
    "answers": [
      {
        "question": "7 + 2 = ?",
        "selected": "9",
        "correct": "9",
        "is_correct": true
      },
      {
        "question": "8 + 3 = ?",
        "selected": "23",
        "correct": "11",
        "is_correct": false
      },
      {
        "question": "9 + 4 = ?",
        "selected": "SDSAd",
        "correct": "13",
        "is_correct": false
      },
      {
        "question": "10 + 5 = ?",
        "selected": "ad",
        "correct": "15",
        "is_correct": false
      },
      {
        "question": "11 + 6 = ?",
        "selected": "2",
        "correct": "17",
        "is_correct": false
      },
      {
        "question": "12 + 7 = ?",
        "selected": "212",
        "correct": "19",
        "is_correct": false
      },
      {
        "question": "13 + 8 = ?",
        "selected": "20",
        "correct": "21",
        "is_correct": false
      },
      {
        "question": "14 + 9 = ?",
        "selected": "12",
        "correct": "23",
        "is_correct": false
      },
      {
        "question": "15 + 1 = ?",
        "selected": "16",
        "correct": "16",
        "is_correct": true
      },
      {
        "question": "16 + 2 = ?",
        "selected": "18",
        "correct": "18",
        "is_correct": true
      },
      {
        "question": "17 + 3 = ?",
        "selected": "23",
        "correct": "20",
        "is_correct": false
      },
      {
        "question": "18 + 4 = ?",
        "selected": "23",
        "correct": "22",
        "is_correct": false
      },
      {
        "question": "19 + 5 = ?",
        "selected": "21",
        "correct": "24",
        "is_correct": false
      },
      {
        "question": "20 + 6 = ?",
        "selected": "12",
        "correct": "26",
        "is_correct": false
      },
      {
        "question": "21 + 7 = ?",
        "selected": "12",
        "correct": "28",
        "is_correct": false
      },
      {
        "question": "22 + 8 = ?",
        "selected": "12",
        "correct": "30",
        "is_correct": false
      },
      {
        "question": "23 + 9 = ?",
        "selected": "12",
        "correct": "32",
        "is_correct": false
      },
      {
        "question": "24 + 1 = ?",
        "selected": "12",
        "correct": "25",
        "is_correct": false
      },
      {
        "question": "25 + 2 = ?",
        "selected": "27",
        "correct": "27",
        "is_correct": true
      },
      {
        "question": "26 + 3 = ?",
        "selected": "29",
        "correct": "29",
        "is_correct": true
      }
    ]
  },
  {
    "student": "TEST",
    "subject": "Math",
    "test_name": "Math Assignment - 13",
    "score": 2,
    "total": 7,
    "percentage": 28.6,
    "duration_seconds": 16,
    "completed_before_timeout": true,
    "start_time": "2026-05-30T19:23:28.378320",
    "end_time": "2026-05-30T19:23:44.686660",
    "answers": [
      {
        "question": "Briana collected 84 pieces of candy on Halloween. Her little sister collected 55 pieces of candy. How many pieces of candy do the girls have altogether?",
        "selected": "140",
        "correct": "139",
        "is_correct": false
      },
      {
        "question": "An animal shelter has 28 puppies available for adoption. On Tuesday, 7 puppies and 13 kittens are adopted. How many puppies are left at the shelter?",
        "selected": "14",
        "correct": "21",
        "is_correct": false
      },
      {
        "question": "Zoe made 39 friendship bracelets and gave 6 away. She then made 10 more friendship bracelets. How many bracelets does Zoe have now?",
        "selected": "43",
        "correct": "43",
        "is_correct": true
      },
      {
        "question": "Fill in the blanks: 5, 10, ___, 20, __, 30, 35, 40 ___, ___",
        "selected": "15, 25, 35, 45",
        "correct": "15, 25, 35, 45",
        "is_correct": true
      },
      {
        "question": "Amir bakes 24 cookies for the school bake sale. Gia bakes 18 cookies for the school bake sale. Amir and Gia work together and sell all but 5 of their cookies. How many cookies did Amir and Gia sell altogether?",
        "selected": "38",
        "correct": "37",
        "is_correct": false
      },
      {
        "question": "Julie counts 23 fish in one pond. She counts 13 more fish in another pond. How many fish does Julie count altogether?",
        "selected": "26",
        "correct": "36",
        "is_correct": false
      },
      {
        "question": "Max has 10 crayons on his desk. He finds 15 more crayons inside his desk. How many crayons does Max have altogether?",
        "selected": "15",
        "correct": "25",
        "is_correct": false
      }
    ]
  },
  {
    "student": "TEST",
    "subject": "Math",
    "test_name": "Math Assignment - 13",
    "score": 2,
    "total": 7,
    "percentage": 28.6,
    "duration_seconds": 21,
    "completed_before_timeout": true,
    "start_time": "2026-05-30T19:23:28.378320",
    "end_time": "2026-05-30T19:23:49.436531",
    "answers": [
      {
        "question": "Briana collected 84 pieces of candy on Halloween. Her little sister collected 55 pieces of candy. How many pieces of candy do the girls have altogether?",
        "selected": "140",
        "correct": "139",
        "is_correct": false
      },
      {
        "question": "An animal shelter has 28 puppies available for adoption. On Tuesday, 7 puppies and 13 kittens are adopted. How many puppies are left at the shelter?",
        "selected": "14",
        "correct": "21",
        "is_correct": false
      },
      {
        "question": "Zoe made 39 friendship bracelets and gave 6 away. She then made 10 more friendship bracelets. How many bracelets does Zoe have now?",
        "selected": "43",
        "correct": "43",
        "is_correct": true
      },
      {
        "question": "Fill in the blanks: 5, 10, ___, 20, __, 30, 35, 40 ___, ___",
        "selected": "15, 25, 35, 45",
        "correct": "15, 25, 35, 45",
        "is_correct": true
      },
      {
        "question": "Amir bakes 24 cookies for the school bake sale. Gia bakes 18 cookies for the school bake sale. Amir and Gia work together and sell all but 5 of their cookies. How many cookies did Amir and Gia sell altogether?",
        "selected": "38",
        "correct": "37",
        "is_correct": false
      },
      {
        "question": "Julie counts 23 fish in one pond. She counts 13 more fish in another pond. How many fish does Julie count altogether?",
        "selected": "26",
        "correct": "36",
        "is_correct": false
      },
      {
        "question": "Max has 10 crayons on his desk. He finds 15 more crayons inside his desk. How many crayons does Max have altogether?",
        "selected": "15",
        "correct": "25",
        "is_correct": false
      }
    ]
  },
  {
    "student": "TEST",
    "subject": "Math",
    "test_name": "Math Assignment - 13",
    "score": 2,
    "total": 7,
    "percentage": 28.6,
    "duration_seconds": 26,
    "completed_before_timeout": true,
    "start_time": "2026-05-30T19:23:28.378320",
    "end_time": "2026-05-30T19:23:54.551898",
    "answers": [
      {
        "question": "Briana collected 84 pieces of candy on Halloween. Her little sister collected 55 pieces of candy. How many pieces of candy do the girls have altogether?",
        "selected": "140",
        "correct": "139",
        "is_correct": false
      },
      {
        "question": "An animal shelter has 28 puppies available for adoption. On Tuesday, 7 puppies and 13 kittens are adopted. How many puppies are left at the shelter?",
        "selected": "14",
        "correct": "21",
        "is_correct": false
      },
      {
        "question": "Zoe made 39 friendship bracelets and gave 6 away. She then made 10 more friendship bracelets. How many bracelets does Zoe have now?",
        "selected": "43",
        "correct": "43",
        "is_correct": true
      },
      {
        "question": "Fill in the blanks: 5, 10, ___, 20, __, 30, 35, 40 ___, ___",
        "selected": "15, 25, 35, 45",
        "correct": "15, 25, 35, 45",
        "is_correct": true
      },
      {
        "question": "Amir bakes 24 cookies for the school bake sale. Gia bakes 18 cookies for the school bake sale. Amir and Gia work together and sell all but 5 of their cookies. How many cookies did Amir and Gia sell altogether?",
        "selected": "38",
        "correct": "37",
        "is_correct": false
      },
      {
        "question": "Julie counts 23 fish in one pond. She counts 13 more fish in another pond. How many fish does Julie count altogether?",
        "selected": "26",
        "correct": "36",
        "is_correct": false
      },
      {
        "question": "Max has 10 crayons on his desk. He finds 15 more crayons inside his desk. How many crayons does Max have altogether?",
        "selected": "15",
        "correct": "25",
        "is_correct": false
      }
    ]
  },
  {
    "student": "TEST",
    "subject": "Math",
    "test_name": "Math Assignment - 13",
    "score": 1,
    "total": 7,
    "percentage": 14.3,
    "duration_seconds": 14,
    "completed_before_timeout": true,
    "start_time": "2026-05-30T19:25:03.000184",
    "end_time": "2026-05-30T19:25:16.503453",
    "answers": [
      {
        "question": "Briana collected 84 pieces of candy on Halloween. Her little sister collected 55 pieces of candy. How many pieces of candy do the girls have altogether?",
        "selected": "140",
        "correct": "139",
        "is_correct": false
      },
      {
        "question": "An animal shelter has 28 puppies available for adoption. On Tuesday, 7 puppies and 13 kittens are adopted. How many puppies are left at the shelter?",
        "selected": "15",
        "correct": "21",
        "is_correct": false
      },
      {
        "question": "Zoe made 39 friendship bracelets and gave 6 away. She then made 10 more friendship bracelets. How many bracelets does Zoe have now?",
        "selected": "42",
        "correct": "43",
        "is_correct": false
      },
      {
        "question": "Fill in the blanks: 5, 10, ___, 20, __, 30, 35, 40 ___, ___",
        "selected": "15, 25, 35, 45",
        "correct": "15, 25, 35, 45",
        "is_correct": true
      },
      {
        "question": "Amir bakes 24 cookies for the school bake sale. Gia bakes 18 cookies for the school bake sale. Amir and Gia work together and sell all but 5 of their cookies. How many cookies did Amir and Gia sell altogether?",
        "selected": "38",
        "correct": "37",
        "is_correct": false
      },
      {
        "question": "Julie counts 23 fish in one pond. She counts 13 more fish in another pond. How many fish does Julie count altogether?",
        "selected": "24",
        "correct": "36",
        "is_correct": false
      },
      {
        "question": "Max has 10 crayons on his desk. He finds 15 more crayons inside his desk. How many crayons does Max have altogether?",
        "selected": "12",
        "correct": "25",
        "is_correct": false
      }
    ]
  },
  {
    "student": "NAVEEN",
    "subject": "Math",
    "test_name": "Math Assignment - 13",
    "score": 0,
    "total": 7,
    "percentage": 0.0,
    "duration_seconds": 14,
    "completed_before_timeout": true,
    "start_time": "2026-05-30T19:32:38.536644",
    "end_time": "2026-05-30T19:32:52.754475",
    "answers": [
      {
        "question": "Briana collected 84 pieces of candy on Halloween. Her little sister collected 55 pieces of candy. How many pieces of candy do the girls have altogether?",
        "selected": "140",
        "correct": "139",
        "is_correct": false
      },
      {
        "question": "An animal shelter has 28 puppies available for adoption. On Tuesday, 7 puppies and 13 kittens are adopted. How many puppies are left at the shelter?",
        "selected": "14",
        "correct": "21",
        "is_correct": false
      },
      {
        "question": "Zoe made 39 friendship bracelets and gave 6 away. She then made 10 more friendship bracelets. How many bracelets does Zoe have now?",
        "selected": "18",
        "correct": "43",
        "is_correct": false
      },
      {
        "question": "Fill in the blanks: 5, 10, ___, 20, __, 30, 35, 40 ___, ___",
        "selected": "10, 25, 35, 45",
        "correct": "15, 25, 35, 45",
        "is_correct": false
      },
      {
        "question": "Amir bakes 24 cookies for the school bake sale. Gia bakes 18 cookies for the school bake sale. Amir and Gia work together and sell all but 5 of their cookies. How many cookies did Amir and Gia sell altogether?",
        "selected": "38",
        "correct": "37",
        "is_correct": false
      },
      {
        "question": "Julie counts 23 fish in one pond. She counts 13 more fish in another pond. How many fish does Julie count altogether?",
        "selected": "12",
        "correct": "36",
        "is_correct": false
      },
      {
        "question": "Max has 10 crayons on his desk. He finds 15 more crayons inside his desk. How many crayons does Max have altogether?",
        "selected": "12",
        "correct": "25",
        "is_correct": false
      }
    ]
  },
  {
    "student": "NAVEEN",
    "subject": "English",
    "test_name": "English Test 1",
    "score": 1,
    "total": 5,
    "percentage": 20.0,
    "duration_seconds": 10,
    "completed_before_timeout": true,
    "start_time": "2026-05-30T19:33:22.392383",
    "end_time": "2026-05-30T19:33:32.199868",
    "answers": [
      {
        "question": "What is the dog's name?",
        "selected": "Tom",
        "correct": "Max",
        "is_correct": false
      },
      {
        "question": "Where do Tom and Max go?",
        "selected": "Mall",
        "correct": "Park",
        "is_correct": false
      },
      {
        "question": "What does Max like to do?",
        "selected": "Run and play",
        "correct": "Run and play",
        "is_correct": true
      },
      {
        "question": "Who owns Max?",
        "selected": "Sam",
        "correct": "Tom",
        "is_correct": false
      },
      {
        "question": "How often do they go to the park?",
        "selected": "Once a week",
        "correct": "Every day",
        "is_correct": false
      }
    ]
  },
  {
    "student": "NAVEEN",
    "subject": "Math",
    "test_name": "Math Assignment - 13",
    "score": 2,
    "total": 7,
    "percentage": 28.6,
    "duration_seconds": 13,
    "completed_before_timeout": true,
    "start_time": "2026-05-30T19:33:43.624676",
    "end_time": "2026-05-30T19:33:56.673544",
    "answers": [
      {
        "question": "Briana collected 84 pieces of candy on Halloween. Her little sister collected 55 pieces of candy. How many pieces of candy do the girls have altogether?",
        "selected": "139",
        "correct": "139",
        "is_correct": true
      },
      {
        "question": "An animal shelter has 28 puppies available for adoption. On Tuesday, 7 puppies and 13 kittens are adopted. How many puppies are left at the shelter?",
        "selected": "14",
        "correct": "21",
        "is_correct": false
      },
      {
        "question": "Zoe made 39 friendship bracelets and gave 6 away. She then made 10 more friendship bracelets. How many bracelets does Zoe have now?",
        "selected": "43",
        "correct": "43",
        "is_correct": true
      },
      {
        "question": "Fill in the blanks: 5, 10, ___, 20, __, 30, 35, 40 ___, ___",
        "selected": "10, 25, 35, 45",
        "correct": "15, 25, 35, 45",
        "is_correct": false
      },
      {
        "question": "Amir bakes 24 cookies for the school bake sale. Gia bakes 18 cookies for the school bake sale. Amir and Gia work together and sell all but 5 of their cookies. How many cookies did Amir and Gia sell altogether?",
        "selected": "38",
        "correct": "37",
        "is_correct": false
      },
      {
        "question": "Julie counts 23 fish in one pond. She counts 13 more fish in another pond. How many fish does Julie count altogether?",
        "selected": "12",
        "correct": "36",
        "is_correct": false
      },
      {
        "question": "Max has 10 crayons on his desk. He finds 15 more crayons inside his desk. How many crayons does Max have altogether?",
        "selected": "14",
        "correct": "25",
        "is_correct": false
      }
    ]
  },
  {
    "student": "NAVEEN",
    "subject": "English",
    "test_name": "English Test 1",
    "score": 3,
    "total": 5,
    "percentage": 60.0,
    "duration_seconds": 8,
    "completed_before_timeout": true,
    "start_time": "2026-05-30T19:34:55.152647",
    "end_time": "2026-05-30T19:35:03.064286",
    "answers": [
      {
        "question": "What is the dog's name?",
        "selected": "Max",
        "correct": "Max",
        "is_correct": true
      },
      {
        "question": "Where do Tom and Max go?",
        "selected": "Mall",
        "correct": "Park",
        "is_correct": false
      },
      {
        "question": "What does Max like to do?",
        "selected": "Run and play",
        "correct": "Run and play",
        "is_correct": true
      },
      {
        "question": "Who owns Max?",
        "selected": "Sam",
        "correct": "Tom",
        "is_correct": false
      },
      {
        "question": "How often do they go to the park?",
        "selected": "Every day",
        "correct": "Every day",
        "is_correct": true
      }
    ]
  },
  {
    "student": "NAVEEN",
    "subject": "English",
    "test_name": "English Test 1",
    "score": 3,
    "total": 5,
    "percentage": 60.0,
    "duration_seconds": 24,
    "completed_before_timeout": true,
    "start_time": "2026-05-30T19:34:55.152647",
    "end_time": "2026-05-30T19:35:19.530191",
    "answers": [
      {
        "question": "What is the dog's name?",
        "selected": "Max",
        "correct": "Max",
        "is_correct": true
      },
      {
        "question": "Where do Tom and Max go?",
        "selected": "Mall",
        "correct": "Park",
        "is_correct": false
      },
      {
        "question": "What does Max like to do?",
        "selected": "Run and play",
        "correct": "Run and play",
        "is_correct": true
      },
      {
        "question": "Who owns Max?",
        "selected": "Sam",
        "correct": "Tom",
        "is_correct": false
      },
      {
        "question": "How often do they go to the park?",
        "selected": "Every day",
        "correct": "Every day",
        "is_correct": true
      }
    ]
  },
  {
    "student": "NAMMI",
    "subject": "English",
    "test_name": "English Test 1",
    "score": 2,
    "total": 5,
    "percentage": 40.0,
    "duration_seconds": 8,
    "completed_before_timeout": true,
    "start_time": "2026-05-30T19:35:29.444522",
    "end_time": "2026-05-30T19:35:37.665590",
    "answers": [
      {
        "question": "What is the dog's name?",
        "selected": "Tom",
        "correct": "Max",
        "is_correct": false
      },
      {
        "question": "Where do Tom and Max go?",
        "selected": "School",
        "correct": "Park",
        "is_correct": false
      },
      {
        "question": "What does Max like to do?",
        "selected": "Sleep",
        "correct": "Run and play",
        "is_correct": false
      },
      {
        "question": "Who owns Max?",
        "selected": "Tom",
        "correct": "Tom",
        "is_correct": true
      },
      {
        "question": "How often do they go to the park?",
        "selected": "Every day",
        "correct": "Every day",
        "is_correct": true
      }
    ]
  },
  {
    "student": "NAVEEN",
    "subject": "English",
    "test_name": "English Test 2",
    "score": 3,
    "total": 5,
    "percentage": 60.0,
    "duration_seconds": 7,
    "completed_before_timeout": true,
    "start_time": "2026-05-30T19:35:53.254907",
    "end_time": "2026-05-30T19:36:00.032799",
    "answers": [
      {
        "question": "What did Lily plant?",
        "selected": "Flower",
        "correct": "Flower",
        "is_correct": true
      },
      {
        "question": "Where did Lily plant it?",
        "selected": "School",
        "correct": "Garden",
        "is_correct": false
      },
      {
        "question": "What did Lily do every day?",
        "selected": "Watered it",
        "correct": "Watered it",
        "is_correct": true
      },
      {
        "question": "What happened after a few weeks?",
        "selected": "It bloomed",
        "correct": "It bloomed",
        "is_correct": true
      },
      {
        "question": "How did the flower become?",
        "selected": "Dry",
        "correct": "Beautiful",
        "is_correct": false
      }
    ]
  },
  {
    "student": "TEST",
    "subject": "English",
    "test_name": "English Test 1",
    "score": 1,
    "total": 5,
    "percentage": 20.0,
    "duration_seconds": 8,
    "completed_before_timeout": true,
    "start_time": "2026-05-30T19:37:53.391441",
    "end_time": "2026-05-30T19:38:01.026096",
    "answers": [
      {
        "question": "What is the dog's name?",
        "selected": "Tom",
        "correct": "Max",
        "is_correct": false
      },
      {
        "question": "Where do Tom and Max go?",
        "selected": "Mall",
        "correct": "Park",
        "is_correct": false
      },
      {
        "question": "What does Max like to do?",
        "selected": "Run and play",
        "correct": "Run and play",
        "is_correct": true
      },
      {
        "question": "Who owns Max?",
        "selected": "Sam",
        "correct": "Tom",
        "is_correct": false
      },
      {
        "question": "How often do they go to the park?",
        "selected": "Once a week",
        "correct": "Every day",
        "is_correct": false
      }
    ]
  }
]